{
  "years": [
    {
      "year": 2025,
      "images": [
        "2025_001.jpg",
        "2025_002.jpg",
        "2025_003.jpg"
      ]
    },
    {
      "year": 2024,
      "images": [
        "2024_001.jpg",
        "2024_002.jpg",
        "2024_003.jpg"
      ]
    },
    {
      "year": 2023,
      "images": [
        "2023_001.jpg",
        "2023_002.jpg",
        "2023_003.jpg"
      ]
    },
    {
      "year": 2022,
      "images": [
        "2022_001.jpg",
        "2022_002.jpg",
        "2022_003.jpg"
      ]
    },
    {
      "year": 2021,
      "images": [
        "2021_001.jpg",
        "2021_002.jpg",
        "2021_003.jpg"
      ]
    }
  ]
}